src/__init__.py
src/sdk/__init__.py
src/sdk/start.py
one_python_demo-0.0.2.dist-info/LICENSE.txt
one_python_demo-0.0.2.dist-info/METADATA
one_python_demo-0.0.2.dist-info/WHEEL
one_python_demo-0.0.2.dist-info/entry_points.txt
one_python_demo-0.0.2.dist-info/top_level.txt
one_python_demo-0.0.2.dist-info/RECORD
